mypythonlib/__init__.py
mypythonlib/myfunctions.py
tests/__init__.py
tests/test_myfunctions.py
searchgenius-0.1.0.dist-info/METADATA
searchgenius-0.1.0.dist-info/WHEEL
searchgenius-0.1.0.dist-info/top_level.txt
searchgenius-0.1.0.dist-info/RECORD
